HSDetector/Analysis.py
HSDetector/MDsimulation.py
HSDetector/__init__.py
HSDetector/align_aa2cg.py
HSDetector/file_copying.py
HSDetector/main.py
HSDetector/membrane_quality_check.py
HSDetector/merge_data.py
HSDetector/rank_pockets.py
HSDetector/run_command_with_retries.py
HSDetector/run_inputs_script.py
HSDetector/system_build.py
HSDetector/tools_cli.py
HSDetector/inputs/__init__.py
HSDetector/inputs/insane.py
HSDetector/inputs/mdp_files/em.mdp
HSDetector/inputs/mdp_files/npt_const.mdp
HSDetector/inputs/mdp_files/npt_noconst_1fs.mdp
HSDetector/inputs/mdp_files/npt_noconst_20fs.mdp
HSDetector/inputs/mdp_files/npt_prod.mdp
HSDetector/inputs/mdp_files/nvt.mdp
HSDetector/inputs/toppar/martini_v3.0.0.itp
HSDetector/inputs/toppar/martini_v3.0.0_ions_v1.itp
HSDetector/inputs/toppar/martini_v3.0.0_phospholipids_v1.itp
HSDetector/inputs/toppar/martini_v3.0.0_solvents_v1.itp
HSDetector/inputs/toppar/martini_v3.0_sterols_v1.0.itp
HSDetector/tools/__init__.py
HSDetector/tools/generate_prm.py
HSDetector/tools/orient_protein.py
hsdetector-0.1.3.dist-info/licenses/LICENSE
hsdetector-0.1.3.dist-info/METADATA
hsdetector-0.1.3.dist-info/WHEEL
hsdetector-0.1.3.dist-info/entry_points.txt
hsdetector-0.1.3.dist-info/top_level.txt
hsdetector-0.1.3.dist-info/RECORD
