Metadata-Version: 2.4
Name: HSDetector
Version: 0.1.3
Summary: Detection of membrane components hot spots around a protein
Author: David Sotillo Núñez
Author-email: David Sotillo Núñez <david.sotillo.bq@gmail.com>
License: MIT
Requires-Python: >=3.8
License-File: LICENSE
Requires-Dist: numpy<2.0
Requires-Dist: vermouth
Requires-Dist: tqdm
Requires-Dist: MDAnalysis
Requires-Dist: lipyphilic==0.10.0
Requires-Dist: matplotlib
Requires-Dist: fortranformat
Requires-Dist: importlib-resources; python_version < "3.9"
Dynamic: license-file
